setup.py
singlefile/__init__.py
singlefile.egg-info/PKG-INFO
singlefile.egg-info/SOURCES.txt
singlefile.egg-info/dependency_links.txt
singlefile.egg-info/requires.txt
singlefile.egg-info/top_level.txt