Metadata-Version: 1.1
Name: singlefile
Version: 0.0.1a0
Summary: import from web. share your snippets and import them from web
Home-page: https://gitlab.com/eightnoteight/singlefile
Author: Srinivas Devaki
Author-email: mr.eightnoteight@gmail.com
License: UNKNOWN
Download-URL: https://gitlab.com/eightnoteight/singlefile/repository/archive.zip?ref=master
Platform: UNKNOWN
Classifier: Intended Audience :: Developers
Classifier: License :: OSI Approved :: MIT License
Classifier: Natural Language :: English
Classifier: Programming Language :: Python :: 3.4
Classifier: Programming Language :: Python :: 3.5
Classifier: Programming Language :: Python :: 3 :: Only
Classifier: Programming Language :: Python :: Implementation :: CPython
Classifier: Topic :: Software Development :: Libraries :: Python Modules
Classifier: Topic :: Utilities
